{"Energie": {"Wind": 0.0, "Solar": 100.0, "Biomasse": 0.0, "Wasser": 0.0, "Anteil": 0.5, "link": "https://www.karten.energieatlas.bayern.de/start/?c=677751,5422939&z=8.01&l=atkis,37864384-e4fe-47de-8227-619bd33e1eda&t=energie"}, "KFZ": {"Jahr": [2018, 2019, 2020, 2021, 2022, 2023], "Benzin": [73762, 75449, 76854, 77023, 75806, 74619], "Diesel": [38794, 38488, 38183, 37955, 37064, 35895], "Hybrid": [454, 673, 1114, 2209, 3827, 5237], "Elektro": [143, 211, 356, 777, 1586, 2698], "Anteil": {"Benzin": 63, "Diesel": 30, "Hybrid": 4, "Elektro": 2}, "link": "https://open.bydata.de/datasets/46251-003-d?locale=de"}, "Bevoelkerung": {"Jahr": [2013, 2014, 2015, 2016, 2017, 2018, 2019, 2020, 2021, 2022, 2023], "Gesamt": [9813, 9793, 9784, 9936, 9990, 9935, 9947, 9999, 10143, 10278, 10257], "Entwicklung": [3, -20, -9, 152, 54, -55, 12, 52, 144, 135, -21], "link": "https://open.bydata.de/datasets/12411-000-d?locale=de"}, "Mobilfunk": {"2G": 100.0, "4G": 99.6, "5G": 95.4, "link": "https://gigabitgrundbuch.bund.de/GIGA/DE/MobilfunkMonitoring/Downloads/start.html"}}